[
	{
		"Institution ID (INS)": "INS:Chapel_Louis_XII",
		"Institution Name": "Chapel of Louis XII",
		"Alias": "French royal court",
		"Institution Description": "chapel of King Louis XII, who reigned from 1498–1515",
		"Input data": "BSO",
		"Date entered": "2024-4-4"
	},
	{
		"Institution ID (INS)": "INS:Chapel_Anne_Brittany",
		"Institution Name": "Chapel of Anne of Brittany",
		"Alias": "French royal court",
		"Institution Description": "chapel of Anne of Brittany, queen from 1491 to 1498 and 1499 to 1514",
		"Input data": "BSO",
		"Date entered": "2024-4-4"
	},
	{
		"Institution ID (INS)": "INS:Chapel_Francis_I",
		"Institution Name": "Chapel of Francis I",
		"Alias": "French royal court",
		"Institution Description": "chapel of Francis I, king from 1515 to 1547",
		"Input data": "BSO",
		"Date entered": "2024-4-5"
	},
	{
		"Institution ID (INS)": "INS:Court_Ferrara",
		"Institution Name": "Court of Ferrara",
		"Alias": "Ferrarese Court",
		"Input data": "BSO",
		"Date entered": "2024-4-9"
	},
	{
		"Institution ID (INS)": "INS:Cappella_Sistina",
		"Institution Name": "Cappella Sistina",
		"Alias": "Sistine Chapel",
		"Input data": "BSO",
		"Date entered": "2024-4-11"
	},
	{
		"Institution ID (INS)": "INS:Chapel_Rene_Anjou",
		"Institution Name": "Chapel of René of Anjou",
		"Input data": "FEM",
		"Date entered": "2024-4-12"
	},
	{
		"Institution ID (INS)": "INS:Troyes_Cathedral",
		"Institution Name": "Troyes Cathedral",
		"Input data": "SMB",
		"Date entered": "2024-6-7"
	},
	{
		"Institution ID (INS)": "INS:Chapel_Charles_I",
		"Institution Name": "Chapel of Charles I",
		"Institution Description": "Chapel of Charles I, Duke of Savoy, and Bianca of Monferrato",
		"Input data": "SMB",
		"Date entered": "2024-6-8"
	}
]